bitmex_tools/__init__.py
bitmex_tools/bitmex_ob_service.py
bitmex_tools/order_book_l2.py
bitmex_tools/sockets/__init__.py
bitmex_tools/sockets/bitmex_socket_orderbook10.py
bitmex_tools/sockets/bitmex_socket_orderbookL2.py
bitmex_tools-1.9.dist-info/METADATA
bitmex_tools-1.9.dist-info/WHEEL
bitmex_tools-1.9.dist-info/top_level.txt
bitmex_tools-1.9.dist-info/RECORD
