Metadata-Version: 2.1
Name: bitmex-tools
Version: 1.9
Summary: Bitmex Tools
Home-page: UNKNOWN
Author: Philippe Remy
License: MIT
Platform: UNKNOWN
Requires-Dist: numpy
Requires-Dist: pandas
Requires-Dist: sortedcontainers
Requires-Dist: websocket-client (==0.47.0)
